fd_converter/__init__.py
fd_converter/__main__.py
fd_converter/ffmpeg.py
fd_converter/gui/__init__.py
fd_converter/gui/__main__.py
fd_converter/utils.py
fd_converter-0.1.1.dist-info/METADATA
fd_converter-0.1.1.dist-info/WHEEL
fd_converter-0.1.1.dist-info/RECORD
