Metadata-Version: 2.1
Name: fd-converter
Version: 0.1.1
Summary: 
Author: dimnissv
Author-email: dimnissv@yandex.kz
Requires-Python: >=3.8,<4.0
Classifier: Programming Language :: Python :: 3
Classifier: Programming Language :: Python :: 3.8
Classifier: Programming Language :: Python :: 3.9
Classifier: Programming Language :: Python :: 3.10
Classifier: Programming Language :: Python :: 3.11
Classifier: Programming Language :: Python :: 3.12
